GetMyIPcawen-1.0.11.data/data/configurations/getmyip.yaml
GetMyIPcawen-1.0.11.data/scripts/getip.py
GetMyIPcawen-1.0.11.dist-info/DESCRIPTION.rst
GetMyIPcawen-1.0.11.dist-info/METADATA
GetMyIPcawen-1.0.11.dist-info/RECORD
GetMyIPcawen-1.0.11.dist-info/WHEEL
GetMyIPcawen-1.0.11.dist-info/metadata.json
GetMyIPcawen-1.0.11.dist-info/top_level.txt
getmyipcawen/__init__.py
getmyipcawen/getmyip.py
getmyipcawen/common/__init__.py
getmyipcawen/common/common.py
